audiobookdl/__init__.py
audiobookdl/__main__.py
audiobookdl/args.py
audiobookdl/config.py
audiobookdl/exceptions.py
audiobookdl/logging.py
audiobookdl/assets/ffmpeg_chapter_template.txt
audiobookdl/assets/simple_help.txt
audiobookdl/assets/errors/book_access.txt
audiobookdl/assets/errors/book_has_no_audiobook.txt
audiobookdl/assets/errors/book_not_found.txt
audiobookdl/assets/errors/book_not_released.txt
audiobookdl/assets/errors/chapters_add.txt
audiobookdl/assets/errors/config_not_found.txt
audiobookdl/assets/errors/data_not_present.txt
audiobookdl/assets/errors/download_error.txt
audiobookdl/assets/errors/failed_combining.txt
audiobookdl/assets/errors/generic.txt
audiobookdl/assets/errors/missing_dependency.txt
audiobookdl/assets/errors/nextory_want_to_read.txt
audiobookdl/assets/errors/no_files_found.txt
audiobookdl/assets/errors/no_source_found.txt
audiobookdl/assets/errors/request_error.txt
audiobookdl/assets/errors/user_not_authorized.txt
audiobookdl/assets/sources/podimo/book_info.graphql
audiobookdl/assets/sources/podimo/files.graphql
audiobookdl/assets/sources/podimo/login.graphql
audiobookdl/assets/sources/podimo/podcast.graphql
audiobookdl/assets/sources/podimo/podcast_episode_file.graphql
audiobookdl/assets/sources/podimo/podcast_episodes.graphql
audiobookdl/output/__init__.py
audiobookdl/output/download.py
audiobookdl/output/encryption.py
audiobookdl/output/output.py
audiobookdl/output/metadata/__init__.py
audiobookdl/output/metadata/ffmpeg.py
audiobookdl/output/metadata/id3.py
audiobookdl/output/metadata/mp4.py
audiobookdl/sources/__init__.py
audiobookdl/sources/audiobooksdotcom.py
audiobookdl/sources/blinkist.py
audiobookdl/sources/bookbeat.py
audiobookdl/sources/chirp.py
audiobookdl/sources/ereolen.py
audiobookdl/sources/everand.py
audiobookdl/sources/librivox.py
audiobookdl/sources/nextory.py
audiobookdl/sources/overdrive.py
audiobookdl/sources/podimo.py
audiobookdl/sources/rss.py
audiobookdl/sources/saxo.py
audiobookdl/sources/storytel.py
audiobook_dl-0.7.3.dist-info/LICENSE
audiobook_dl-0.7.3.dist-info/METADATA
audiobook_dl-0.7.3.dist-info/WHEEL
audiobook_dl-0.7.3.dist-info/entry_points.txt
audiobook_dl-0.7.3.dist-info/top_level.txt
audiobook_dl-0.7.3.dist-info/RECORD
