Metadata-Version: 2.1
Name: audiobook-dl
Version: 0.7.3
Summary: CLI tool for downloading audiobooks from online sources
Author-email: Joakim Holm <mail@joakimholm.xyz>
Project-URL: Homepage, https://github.com/jo1gi/audiobook-dl
Project-URL: Bugtracker, https://github.com/jo1gi/audiobook-dl/issues
Keywords: audiobooks,cli,downloader
Classifier: Programming Language :: Python :: 3
Classifier: Topic :: Multimedia :: Sound/Audio
Classifier: License :: OSI Approved :: GNU General Public License v3 (GPLv3)
License-File: LICENSE
Requires-Dist: appdirs
Requires-Dist: attrs
Requires-Dist: cssselect
Requires-Dist: importlib-resources
Requires-Dist: lxml
Requires-Dist: m3u8
Requires-Dist: mutagen
Requires-Dist: pillow
Requires-Dist: pycryptodome
Requires-Dist: requests
Requires-Dist: rich
Requires-Dist: tomli
Requires-Dist: pycountry
